asm_sql_python_crud/__init__.py
asm_sql_python_crud/managers.py
asm_sql_python_crud/models.py
asm_sql_python_crud/routers.py
asm_sql_python_crud/settings.py
asm_sql_python_crud/utils.py
asm_sql_python_crud/viewsets.py
asm_sql_python_crud-1.0.0.dist-info/METADATA
asm_sql_python_crud-1.0.0.dist-info/WHEEL
asm_sql_python_crud-1.0.0.dist-info/top_level.txt
asm_sql_python_crud-1.0.0.dist-info/RECORD
